auto_parse/__init__.py
spider_auto_parse-1.0.1.dist-info/METADATA
spider_auto_parse-1.0.1.dist-info/WHEEL
spider_auto_parse-1.0.1.dist-info/top_level.txt
spider_auto_parse-1.0.1.dist-info/RECORD
