Metadata-Version: 2.1
Name: spider-auto-parse
Version: 1.0.1
Summary: 自动解析详情、时间、列表
Home-page: https://blog.csdn.net/m0_50889678/article/details/122344474
Author: xueqiuyu
Author-email: xueqy.boot@foxmail.com
License: UNKNOWN
Platform: UNKNOWN
Requires-Dist: cchardet
Requires-Dist: dateparser
Requires-Dist: Distance
Requires-Dist: environs
Requires-Dist: joblib
Requires-Dist: loguru
Requires-Dist: lxml
Requires-Dist: matplotlib
Requires-Dist: numpy
Requires-Dist: python-Levenshtein
Requires-Dist: readability-lxml
Requires-Dist: requests
Requires-Dist: scikit-learn
Requires-Dist: setuptools
Requires-Dist: w3lib
